{
  "__type__": "cc.TextAsset",
  "_name": "char_2.atlas",
  "_objFlags": 0,
  "_native": "",
  "text": "\r\nchar_2.png\r\nsize: 1256,272\r\nformat: RGBA8888\r\nfilter: Linear,Linear\r\nrepeat: none\r\nDear\r\n  rotate: false\r\n  xy: 2, 71\r\n  size: 165, 199\r\n  orig: 165, 199\r\n  offset: 0, 0\r\n  index: -1\r\nLayer 158\r\n  rotate: false\r\n  xy: 561, 117\r\n  size: 327, 153\r\n  orig: 327, 153\r\n  offset: 0, 0\r\n  index: -1\r\nLayer 160\r\n  rotate: false\r\n  xy: 344, 14\r\n  size: 75, 80\r\n  orig: 75, 80\r\n  offset: 0, 0\r\n  index: -1\r\nLayer 163\r\n  rotate: true\r\n  xy: 169, 83\r\n  size: 187, 111\r\n  orig: 187, 111\r\n  offset: 0, 0\r\n  index: -1\r\nLayer 164\r\n  rotate: true\r\n  xy: 457, 110\r\n  size: 160, 102\r\n  orig: 160, 102\r\n  offset: 0, 0\r\n  index: -1\r\nLayer 165\r\n  rotate: false\r\n  xy: 282, 96\r\n  size: 173, 174\r\n  orig: 173, 174\r\n  offset: 0, 0\r\n  index: -1\r\nbg_eye_1\r\n  rotate: false\r\n  xy: 1225, 110\r\n  size: 26, 17\r\n  orig: 26, 17\r\n  offset: 0, 0\r\n  index: -1\r\nbg_eye_2\r\n  rotate: false\r\n  xy: 1211, 65\r\n  size: 17, 16\r\n  orig: 17, 16\r\n  offset: 0, 0\r\n  index: -1\r\near\r\n  rotate: false\r\n  xy: 754, 12\r\n  size: 30, 42\r\n  orig: 30, 42\r\n  offset: 0, 0\r\n  index: -1\r\nef_smoke\r\n  rotate: false\r\n  xy: 2, 2\r\n  size: 71, 67\r\n  orig: 71, 67\r\n  offset: 0, 0\r\n  index: -1\r\neye\r\n  rotate: true\r\n  xy: 860, 15\r\n  size: 39, 32\r\n  orig: 39, 32\r\n  offset: 0, 0\r\n  index: -1\r\neye_1\r\n  rotate: true\r\n  xy: 1191, 99\r\n  size: 28, 32\r\n  orig: 28, 32\r\n  offset: 0, 0\r\n  index: -1\r\neye_2\r\n  rotate: false\r\n  xy: 1225, 83\r\n  size: 25, 25\r\n  orig: 25, 25\r\n  offset: 0, 0\r\n  index: -1\r\neye_3\r\n  rotate: true\r\n  xy: 867, 80\r\n  size: 35, 24\r\n  orig: 35, 24\r\n  offset: 0, 0\r\n  index: -1\r\neyesbrown\r\n  rotate: true\r\n  xy: 786, 14\r\n  size: 40, 13\r\n  orig: 40, 13\r\n  offset: 0, 0\r\n  index: -1\r\neyesbrown_1\r\n  rotate: true\r\n  xy: 867, 56\r\n  size: 22, 16\r\n  orig: 22, 16\r\n  offset: 0, 0\r\n  index: -1\r\nface\r\n  rotate: false\r\n  xy: 890, 129\r\n  size: 117, 141\r\n  orig: 117, 141\r\n  offset: 0, 0\r\n  index: -1\r\nface_2\r\n  rotate: true\r\n  xy: 905, 11\r\n  size: 116, 141\r\n  orig: 116, 141\r\n  offset: 0, 0\r\n  index: -1\r\nface_3\r\n  rotate: false\r\n  xy: 1009, 129\r\n  size: 116, 141\r\n  orig: 116, 141\r\n  offset: 0, 0\r\n  index: -1\r\nface_4\r\n  rotate: true\r\n  xy: 1048, 11\r\n  size: 116, 141\r\n  orig: 116, 141\r\n  offset: 0, 0\r\n  index: -1\r\nface_5\r\n  rotate: false\r\n  xy: 1127, 129\r\n  size: 116, 141\r\n  orig: 116, 141\r\n  offset: 0, 0\r\n  index: -1\r\nhand_1\r\n  rotate: false\r\n  xy: 75, 5\r\n  size: 46, 64\r\n  orig: 46, 64\r\n  offset: 0, 0\r\n  index: -1\r\nhand_2\r\n  rotate: false\r\n  xy: 543, 5\r\n  size: 41, 103\r\n  orig: 41, 103\r\n  offset: 0, 0\r\n  index: -1\r\nhand_3\r\n  rotate: true\r\n  xy: 693, 2\r\n  size: 38, 59\r\n  orig: 38, 59\r\n  offset: 0, 0\r\n  index: -1\r\nhand_4\r\n  rotate: true\r\n  xy: 629, 2\r\n  size: 38, 62\r\n  orig: 38, 62\r\n  offset: 0, 0\r\n  index: -1\r\nhand_5\r\n  rotate: true\r\n  xy: 801, 15\r\n  size: 39, 57\r\n  orig: 39, 57\r\n  offset: 0, 0\r\n  index: -1\r\nheart2\r\n  rotate: false\r\n  xy: 248, 2\r\n  size: 94, 79\r\n  orig: 94, 79\r\n  offset: 0, 0\r\n  index: -1\r\nhip\r\n  rotate: false\r\n  xy: 629, 42\r\n  size: 117, 73\r\n  orig: 117, 73\r\n  offset: 0, 0\r\n  index: -1\r\nm_1\r\n  rotate: true\r\n  xy: 1191, 80\r\n  size: 17, 18\r\n  orig: 17, 18\r\n  offset: 0, 0\r\n  index: -1\r\nm_2\r\n  rotate: false\r\n  xy: 885, 60\r\n  size: 18, 18\r\n  orig: 18, 18\r\n  offset: 0, 0\r\n  index: -1\r\nneck\r\n  rotate: true\r\n  xy: 421, 16\r\n  size: 78, 120\r\n  orig: 78, 120\r\n  offset: 0, 0\r\n  index: -1\r\nshoulder\r\n  rotate: true\r\n  xy: 123, 6\r\n  size: 63, 123\r\n  orig: 63, 123\r\n  offset: 0, 0\r\n  index: -1\r\nshoulder_1\r\n  rotate: false\r\n  xy: 586, 13\r\n  size: 41, 102\r\n  orig: 41, 102\r\n  offset: 0, 0\r\n  index: -1\r\nshoulder_2\r\n  rotate: true\r\n  xy: 748, 56\r\n  size: 59, 117\r\n  orig: 59, 117\r\n  offset: 0, 0\r\n  index: -1\r\n"
}